sunagent_ext/__init__.py
sunagent_ext/py.typed
sunagent_ext/agents/__init__.py
sunagent_ext/agents/_assistant_agent.py
sunagent_ext/cache_store/__init__.py
sunagent_ext/cache_store/diskcache.py
sunagent_ext/cache_store/redis.py
sunagent_ext/memory/__init__.py
sunagent_ext/memory/_base_memory.py
sunagent_ext/memory/_mem0x_memory.py
sunagent_ext/memory/_profile_memory.py
sunagent_ext/secret_management/__init__.py
sunagent_ext/secret_management/config.py
sunagent_ext/secret_management/onepassword/__init__.py
sunagent_ext/secret_management/onepassword/_onepassword_client.py
sunagent_ext-0.0.5.dist-info/METADATA
sunagent_ext-0.0.5.dist-info/WHEEL
sunagent_ext-0.0.5.dist-info/licenses/LICENSE-CODE
sunagent_ext-0.0.5.dist-info/RECORD
