Metadata-Version: 2.4
Name: sunagent-ext
Version: 0.0.5
Summary: AutoGen extensions library
License:     MIT License
License-File: LICENSE-CODE
Classifier: License :: OSI Approved :: MIT License
Classifier: Operating System :: OS Independent
Classifier: Programming Language :: Python :: 3
Requires-Python: >=3.10
Requires-Dist: aiohttp
Requires-Dist: autogen-core==0.4.9
Requires-Dist: onepassword-sdk>=0.3.0
Provides-Extra: azure
Requires-Dist: azure-ai-inference>=1.0.0b7; extra == 'azure'
Requires-Dist: azure-core; extra == 'azure'
Requires-Dist: azure-identity; extra == 'azure'
Provides-Extra: langchain
Requires-Dist: langchain-core~=0.3.3; extra == 'langchain'
